mechachainsaw/__init__.py
mechachainsaw/mechachainsaw.py
mechachainsaw-1.21.dist-info/LICENSE.md
mechachainsaw-1.21.dist-info/METADATA
mechachainsaw-1.21.dist-info/WHEEL
mechachainsaw-1.21.dist-info/top_level.txt
mechachainsaw-1.21.dist-info/RECORD
