Metadata-Version: 2.1
Name: mechachainsaw
Version: 1.21
Summary: An easy to use logging wrapper.
Home-page: https://github.com/FuelRats/mechachainsaw
Author: The Fuel Rats Mischief
Author-email: shatt@fuelrats.com
License: BSD-3-Clause
Platform: UNKNOWN
Classifier: Programming Language :: Python :: 3
Classifier: License :: OSI Approved :: BSD License
Classifier: Operating System :: OS Independent
Classifier: Development Status :: 5 - Production/Stable
Classifier: Intended Audience :: Developers
Requires-Dist: coloredlogs
